{ 
   "resourceType":"Organization",
   "active":true,
   "type":[ 
      { 
         "coding":[ 
            { 
               "system":"http://hl7.org/fhir/organization-type",
               "code":"ins",
               "display":"Insurance Company"
            }
         ],
         "text":"Insurance Company"
      }
   ],
   "name":"HealthGorilla",
   "telecom":[ 
      { 
         "system":"phone",
         "value":"1 (844) 446-7455"
      }
   ],
   "address":[ 
      { 
         "line":[ 
            "185 N Wolfe Rd"
         ],
         "city":"Sunnyvale",
         "state":"CA",
         "postalCode":"94085",
         "country":"USA"
      }
   ]
}
